tm_profiler/__init__.py
tm_profiler/tm_profiler.py
tm_profiler-3.0.1.dist-info/licenses/LICENSE
tm_profiler-3.0.1.dist-info/METADATA
tm_profiler-3.0.1.dist-info/WHEEL
tm_profiler-3.0.1.dist-info/top_level.txt
tm_profiler-3.0.1.dist-info/RECORD
